mastercard_personalized_loyalty_offers-1.0.5.dist-info/DESCRIPTION.rst
mastercard_personalized_loyalty_offers-1.0.5.dist-info/METADATA
mastercard_personalized_loyalty_offers-1.0.5.dist-info/RECORD
mastercard_personalized_loyalty_offers-1.0.5.dist-info/WHEEL
mastercard_personalized_loyalty_offers-1.0.5.dist-info/metadata.json
mastercard_personalized_loyalty_offers-1.0.5.dist-info/top_level.txt
mastercardpersonalizedloyaltyoffers/__init__.py
mastercardpersonalizedloyaltyoffers/activatestatementcreditoffer.py
mastercardpersonalizedloyaltyoffers/matchedoffers.py
mastercardpersonalizedloyaltyoffers/offerdetails.py
mastercardpersonalizedloyaltyoffers/redeemedoffers.py
mastercardpersonalizedloyaltyoffers/resourceconfig.py
mastercardpersonalizedloyaltyoffers/statementcreditactivationdetail.py
mastercardpersonalizedloyaltyoffers/userfeedback.py
mastercardpersonalizedloyaltyoffers/usersaving.py
mastercardpersonalizedloyaltyoffers/usertoken.py
